{
  "main": {
    "id": "fa0dfd4841ac8d1c",
    "type": "split",
    "children": [
      {
        "id": "cf86e3e8875572f8",
        "type": "tabs",
        "children": [
          {
            "id": "a6134b52db275248",
            "type": "leaf",
            "state": {
              "type": "empty",
              "state": {}
            }
          }
        ]
      }
    ],
    "direction": "vertical"
  },
  "left": {
    "id": "ed494e132632a761",
    "type": "split",
    "children": [
      {
        "id": "c3f81db74c1f08ea",
        "type": "tabs",
        "children": [
          {
            "id": "af2ffe2583e25ab2",
            "type": "leaf",
            "state": {
              "type": "file-explorer",
              "state": {
                "sortOrder": "alphabetical"
              }
            }
          },
          {
            "id": "bece42ef7aa27daf",
            "type": "leaf",
            "state": {
              "type": "search",
              "state": {
                "query": "",
                "matchingCase": false,
                "explainSearch": false,
                "collapseAll": false,
                "extraContext": false,
                "sortOrder": "alphabetical"
              }
            }
          },
          {
            "id": "074ddd42c2cd61dc",
            "type": "leaf",
            "state": {
              "type": "bookmarks",
              "state": {}
            }
          }
        ]
      }
    ],
    "direction": "horizontal",
    "width": 300
  },
  "right": {
    "id": "5580135a3d2a8a11",
    "type": "split",
    "children": [
      {
        "id": "50e9332de893527e",
        "type": "tabs",
        "children": [
          {
            "id": "5d647c58b50500ba",
            "type": "leaf",
            "state": {
              "type": "backlink",
              "state": {
                "collapseAll": false,
                "extraContext": false,
                "sortOrder": "alphabetical",
                "showSearch": false,
                "searchQuery": "",
                "backlinkCollapsed": false,
                "unlinkedCollapsed": true
              }
            }
          },
          {
            "id": "e66a49ac0a34ccf6",
            "type": "leaf",
            "state": {
              "type": "outgoing-link",
              "state": {
                "linksCollapsed": false,
                "unlinkedCollapsed": true
              }
            }
          },
          {
            "id": "15ff4bd3e1bc7f2e",
            "type": "leaf",
            "state": {
              "type": "tag",
              "state": {
                "sortOrder": "frequency",
                "useHierarchy": true
              }
            }
          },
          {
            "id": "b98d8dc2d232db22",
            "type": "leaf",
            "state": {
              "type": "outline",
              "state": {}
            }
          }
        ]
      }
    ],
    "direction": "horizontal",
    "width": 300,
    "collapsed": true
  },
  "left-ribbon": {
    "hiddenItems": {
      "switcher:打开快速切换": false,
      "graph:查看关系图谱": false,
      "canvas:新建白板": false,
      "daily-notes:打开/创建今天的日记": false,
      "templates:插入模板": false,
      "command-palette:打开命令面板": false
    }
  },
  "active": "a6134b52db275248",
  "lastOpenFiles": [
    "node_modules/xml-name-validator/lib/xml-name-validator.js",
    "node_modules/xml-name-validator/lib",
    "node_modules/stylus/node_modules/source-map/dist/source-map.js",
    "node_modules/stylus/node_modules/source-map/dist",
    "node_modules/string_decoder/lib/string_decoder.js",
    "node_modules/string_decoder/lib",
    "node_modules/prismjs/plugins/unescaped-markup/prism-unescaped-markup.min.js",
    "node_modules/prismjs/plugins/unescaped-markup/prism-unescaped-markup.min.css",
    "node_modules/prismjs/plugins/unescaped-markup/prism-unescaped-markup.js",
    "node_modules/prismjs/plugins/unescaped-markup/prism-unescaped-markup.css",
    "node_modules/prismjs/plugins/unescaped-markup",
    "node_modules/hexo-generator-archive/README.md",
    "node_modules/hexo-cli/assets/source/_posts/hello-world.md",
    "node_modules/highlight.js/styles/brown-papersq.png",
    "node_modules/highlight.js/VERSION_11_UPGRADE.md",
    "node_modules/highlight.js/VERSION_10_UPGRADE.md",
    "node_modules/highlight.js/SUPPORTED_LANGUAGES.md",
    "node_modules/highlight.js/SECURITY.md",
    "node_modules/highlight.js/README.md",
    "node_modules/highlight.js/CHANGES.md",
    "node_modules/hexo-cli/assets/scaffolds/post.md",
    "node_modules/hexo-cli/assets/scaffolds/page.md",
    "node_modules/hexo-cli/assets/scaffolds/draft.md",
    "node_modules/marked/LICENSE.md",
    "node_modules/https-proxy-agent/node_modules/debug/README.md",
    "node_modules/readable-stream/CONTRIBUTING.md",
    "node_modules/agent-base/node_modules/debug/README.md",
    "node_modules/hexo-generator-index/README.md",
    "node_modules/@adobe/css-tools/Readme.md",
    "node_modules/whatwg-mimetype/README.md",
    "node_modules/hexo-renderer-marked/README.md",
    "node_modules/hexo-server/README.md",
    "node_modules/nunjucks/README.md",
    "node_modules/js-yaml-js-types/README.md",
    "node_modules/hexo-i18n/README.md",
    "node_modules/titlecase/README.md",
    "node_modules/titlecase/LICENCE.md",
    "node_modules/hexo-theme-landscape/source/css/images/banner.jpg",
    "node_modules/nib/iconic/iconic_stroke.svg",
    "node_modules/psl/browserstack-logo.svg"
  ]
}